prototorch/models/__init__.py
prototorch/models/abstract.py
prototorch/models/callbacks.py
prototorch/models/cbc.py
prototorch/models/extras.py
prototorch/models/glvq.py
prototorch/models/knn.py
prototorch/models/lvq.py
prototorch/models/probabilistic.py
prototorch/models/unsupervised.py
prototorch/models/vis.py
prototorch_models-0.7.1.dist-info/LICENSE
prototorch_models-0.7.1.dist-info/METADATA
prototorch_models-0.7.1.dist-info/WHEEL
prototorch_models-0.7.1.dist-info/top_level.txt
prototorch_models-0.7.1.dist-info/RECORD
