Metadata-Version: 2.1
Name: prototorch-models
Version: 0.7.1
Summary: Pre-packaged prototype-based machine learning models using ProtoTorch and PyTorch-Lightning.
Author-email: Jensun Ravichandran <jjensun@gmail.com>, Alexander Engelsberger <engelsbe@hs-mittweida.de>
License: MIT
Project-URL: Homepage, https://github.com/si-cim/prototorch_models
Project-URL: Downloads, https://github.com/si-cim/prototorch_models.git
Classifier: Development Status :: 2 - Pre-Alpha
Classifier: Environment :: Plugins
Classifier: Intended Audience :: Developers
Classifier: Intended Audience :: Education
Classifier: Intended Audience :: Science/Research
Classifier: License :: OSI Approved :: MIT License
Classifier: Natural Language :: English
Classifier: Operating System :: OS Independent
Classifier: Programming Language :: Python :: 3
Classifier: Programming Language :: Python :: 3.10
Classifier: Programming Language :: Python :: 3.11
Classifier: Programming Language :: Python :: 3.8
Classifier: Programming Language :: Python :: 3.9
Classifier: Topic :: Scientific/Engineering :: Artificial Intelligence
Classifier: Topic :: Software Development :: Libraries
Classifier: Topic :: Software Development :: Libraries :: Python Modules
Requires-Python: >=3.8
License-File: LICENSE
Requires-Dist: lightning >=2.0.0
Requires-Dist: prototorch >=0.7.5
Provides-Extra: all
Requires-Dist: bumpversion ; extra == 'all'
Requires-Dist: pre-commit ; extra == 'all'
Requires-Dist: yapf ; extra == 'all'
Requires-Dist: toml ; extra == 'all'
Requires-Dist: pytest ; extra == 'all'
Requires-Dist: matplotlib ; extra == 'all'
Requires-Dist: scikit-learn ; extra == 'all'
Requires-Dist: recommonmark ; extra == 'all'
Requires-Dist: nbsphinx ; extra == 'all'
Requires-Dist: sphinx ; extra == 'all'
Requires-Dist: sphinx-rtd-theme ; extra == 'all'
Requires-Dist: sphinxcontrib-bibtex ; extra == 'all'
Requires-Dist: sphinxcontrib-katex ; extra == 'all'
Requires-Dist: ipykernel ; extra == 'all'
Provides-Extra: ci
Requires-Dist: pytest ; extra == 'ci'
Requires-Dist: pre-commit ; extra == 'ci'
Provides-Extra: dev
Requires-Dist: bumpversion ; extra == 'dev'
Requires-Dist: pre-commit ; extra == 'dev'
Requires-Dist: yapf ; extra == 'dev'
Requires-Dist: toml ; extra == 'dev'
Provides-Extra: docs
Requires-Dist: recommonmark ; extra == 'docs'
Requires-Dist: nbsphinx ; extra == 'docs'
Requires-Dist: sphinx ; extra == 'docs'
Requires-Dist: sphinx-rtd-theme ; extra == 'docs'
Requires-Dist: sphinxcontrib-bibtex ; extra == 'docs'
Requires-Dist: sphinxcontrib-katex ; extra == 'docs'
Requires-Dist: ipykernel ; extra == 'docs'
Provides-Extra: examples
Requires-Dist: matplotlib ; extra == 'examples'
Requires-Dist: scikit-learn ; extra == 'examples'
